llmuri/__init__.py
llmuri/llmuri.py
llmuri-0.1.0.dist-info/LICENSE
llmuri-0.1.0.dist-info/METADATA
llmuri-0.1.0.dist-info/WHEEL
llmuri-0.1.0.dist-info/top_level.txt
llmuri-0.1.0.dist-info/RECORD
