Metadata-Version: 2.1
Name: llmuri
Version: 0.1.0
Summary: LLM URI Parsing.
Home-page: https://github.com/marhar/llmuri
Author: Mark Harrison
Author-email: mark@tigereye.com
Classifier: Programming Language :: Python :: 3
Classifier: License :: OSI Approved :: MIT License
Classifier: Operating System :: OS Independent
Requires-Python: >=3.6
License-File: LICENSE
